{
  "id": 6000182,
  "Name": "矿岩机麋",
  "Type": "",
  "Intensity": "",
  "Place": "",
  "Code": "R60-",
  "desc": "召唤矿岩机麋，造成导电伤害。",
  "Rarity": [
    2,
    3,
    4,
    5
  ],
  "Group": [
    "24"
  ],
  "affixData": {
    "text": "使用声骸技能，召唤矿岩机麋，蓄力一击对敌人造成$[0]的导电伤害。技能冷却：$[1]秒",
    "datas": {
      "0": [
        "132.00%",
        "158.40%",
        "184.80%",
        "211.20%",
        "237.60%"
      ],
      "1": [
        "20",
        "20",
        "20",
        "20",
        "20"
      ]
    }
  }
}