{
  "id": 1306,
  "name": "奥古斯塔",
  "abbr": "奥古斯塔",
  "title": "未曜的磁律",
  "star": 5,
  "elem": "electro",
  "allegiance": "黎那汐塔",
  "weapon": "broadblade",
  "birth": "未知",
  "desc": "七丘的现任总督。长照不灭的烈阳，所向披靡的旗帜。她来，她见，她征服。她高擎锋刃，等待着下一个挑战者，抑或是无可抗拒的命运。",
  "cncv": "穆雪婷",
  "jpcv": "日笠阳子",
  "costume": false,
  "tag": {
    "keys": [
      "2",
      "5",
      "13"
    ],
    "name": [
      "主力输出",
      "重击伤害",
      "伤害加深"
    ]
  },
  "ver": 1,
  "baseAttr": {
    "hp": 10300,
    "atk": 462.5,
    "def": 1112.2202
  },
  "Weakness": {
    "ratio": 10000,
    "mastery": 0
  },
  "materials": {
    "boss": "群儡的秽冕",
    "specialty": "辉光金盏",
    "normal": "全频潮蚀帆核",
    "talent": "海蚀嵌合体239",
    "weekly": "鸢尾盛开之日"
  },
  "talent": {
    "a": {
      "name": "逐狩",
      "desc": [
        "<h3>普攻</h3>",
        "进行最多4段的连续攻击，造成导电伤害。",
        "<h3>重击·鸣铁</h3>",
        "消耗耐力攻击目标，造成导电伤害。施放后短时间内短按普攻，可以施放普攻第2段。",
        "<h3>空中攻击</h3>",
        "消耗耐力进行空中下落攻击，造成导电伤害。",
        "<h3>闪避反击</h3>",
        "成功闪避后一定时间内短按普攻，将会攻击目标，造成导电伤害。",
        "<h3>空中闪避反击</h3>",
        "空中成功闪避后一定时间内短按普攻，消耗耐力进行空中下落攻击，造成导电伤害。",
        "<h3>重击·烁雷·后撤</h3>",
        "【战势】满时，重击·鸣铁替换为重击·烁雷·后撤，造成导电伤害，施放时消耗全部的【战势】。",
        "·技能施放时，一定时间后松开普攻，或者再次短按普攻，可以施放重击·烁雷·旋切。",
        "·技能被打断后一定时间内若没有离开地面，亦可施放重击·烁雷·旋切。",
        "<h3>重击·烁雷·旋切</h3>",
        "奥古斯塔舞剑旋转，造成导电伤害。",
        "<h3>重击·烁雷·升拳</h3>",
        "【战势】满时，短按跳跃可以施放重击·烁雷·升拳，造成导电伤害，施放时消耗全部的【战势】。",
        "当施放共鸣技能·斩锋时，若【战势】满，短按共鸣技能或跳跃可以施放重击·烁雷·升拳，造成导电伤害，施放时消耗全部的【战势】。",
        "当施放重击·鸣铁或闪避反击·重击·鸣铁时，若【战势】满，一定时间后松开普攻，或者再次短按普攻或跳跃可以施放重击·烁雷·升拳，造成导电伤害，施放时消耗全部的【战势】。",
        "<h3>闪避反击·重击·鸣铁</h3>",
        "【战势】满时，闪避反击替换为闪避反击·重击·鸣铁，造成导电伤害，此次伤害为重击伤害。",
        "<h3>闪避反击·烁雷·后撤</h3>",
        "【权炳】满时，地面闪避成功后短按普攻，闪避反击与闪避反击·重击·鸣铁替换为闪避反击·烁雷·后撤，施放时造成导电伤害，此次伤害为重击伤害。",
        "·技能施放时，一定时间后松开普攻，或者再次短按普攻，可以施放重击·烁雷·旋切。",
        "·技能被打断后一定时间内若没有离开地面，亦可施放重击·烁雷·旋切。",
        "<h3>【战势】获取规则</h3>",
        "【战势】上限为100点。",
        "·普攻、重击·鸣铁、空中攻击、空中闪避反击、共鸣技能·斩锋、闪避反击、闪避反击·重击·鸣铁造成伤害时可以获得【战势】。",
        "·施放变奏技能·灼金的巡行时，回满【战势】。"
      ],
      "tables": [
        {
          "name": "第一段伤害",
          "isSame": false,
          "values": [
            "28.90%",
            "31.27%",
            "33.64%",
            "36.96%",
            "39.33%",
            "42.06%",
            "45.85%",
            "49.64%",
            "53.43%",
            "57.46%",
            "62.20%",
            "66.94%",
            "71.68%",
            "76.42%",
            "81.16%",
            "85.90%",
            "90.64%",
            "95.38%",
            "100.12%",
            "104.86%"
          ]
        },
        {
          "name": "第二段伤害",
          "isSame": false,
          "values": [
            "33.70%*2",
            "36.47%*2",
            "39.23%*2",
            "43.10%*2",
            "45.86%*2",
            "49.04%*2",
            "53.46%*2",
            "57.88%*2",
            "62.31%*2",
            "67.00%*2",
            "72.53%*2",
            "78.06%*2",
            "83.58%*2",
            "89.11%*2",
            "94.64%*2",
            "100.16%*2",
            "105.69%*2",
            "111.22%*2",
            "116.75%*2",
            "122.27%*2"
          ]
        },
        {
          "name": "第三段伤害",
          "isSame": false,
          "values": [
            "33.00%*3",
            "35.71%*3",
            "38.42%*3",
            "42.21%*3",
            "44.91%*3",
            "48.02%*3",
            "52.35%*3",
            "56.68%*3",
            "61.01%*3",
            "65.61%*3",
            "71.02%*3",
            "76.44%*3",
            "81.85%*3",
            "87.26%*3",
            "92.67%*3",
            "98.08%*3",
            "103.50%*3",
            "108.91%*3",
            "114.32%*3",
            "119.73%*3"
          ]
        },
        {
          "name": "第四段伤害",
          "isSame": false,
          "values": [
            "32.51%*3",
            "35.18%*3",
            "37.84%*3",
            "41.57%*3",
            "44.24%*3",
            "47.30%*3",
            "51.57%*3",
            "55.83%*3",
            "60.10%*3",
            "64.63%*3",
            "69.96%*3",
            "75.29%*3",
            "80.62%*3",
            "85.95%*3",
            "91.28%*3",
            "96.61%*3",
            "101.94%*3",
            "107.27%*3",
            "112.61%*3",
            "117.94%*3"
          ]
        },
        {
          "name": "重击·鸣铁伤害",
          "isSame": false,
          "values": [
            "23.34%*3",
            "25.25%*3",
            "27.16%*3",
            "29.84%*3",
            "31.76%*3",
            "33.96%*3",
            "37.02%*3",
            "40.08%*3",
            "43.14%*3",
            "46.39%*3",
            "50.22%*3",
            "54.05%*3",
            "57.87%*3",
            "61.70%*3",
            "65.53%*3",
            "69.35%*3",
            "73.18%*3",
            "77.01%*3",
            "80.83%*3",
            "84.66%*3"
          ]
        },
        {
          "name": "空中攻击伤害",
          "isSame": false,
          "values": [
            "30.00%*2",
            "32.46%*2",
            "34.92%*2",
            "38.37%*2",
            "40.83%*2",
            "43.66%*2",
            "47.59%*2",
            "51.53%*2",
            "55.47%*2",
            "59.65%*2",
            "64.57%*2",
            "69.49%*2",
            "74.41%*2",
            "79.33%*2",
            "84.25%*2",
            "89.17%*2",
            "94.09%*2",
            "99.01%*2",
            "103.93%*2",
            "108.85%*2"
          ]
        },
        {
          "name": "闪避反击伤害",
          "isSame": false,
          "values": [
            "33.70%*2",
            "36.47%*2",
            "39.23%*2",
            "43.10%*2",
            "45.86%*2",
            "49.04%*2",
            "53.46%*2",
            "57.88%*2",
            "62.31%*2",
            "67.00%*2",
            "72.53%*2",
            "78.06%*2",
            "83.58%*2",
            "89.11%*2",
            "94.64%*2",
            "100.16%*2",
            "105.69%*2",
            "111.22%*2",
            "116.75%*2",
            "122.27%*2"
          ]
        },
        {
          "name": "空中闪避反击伤害",
          "isSame": false,
          "values": [
            "30.00%*2",
            "32.46%*2",
            "34.92%*2",
            "38.37%*2",
            "40.83%*2",
            "43.66%*2",
            "47.59%*2",
            "51.53%*2",
            "55.47%*2",
            "59.65%*2",
            "64.57%*2",
            "69.49%*2",
            "74.41%*2",
            "79.33%*2",
            "84.25%*2",
            "89.17%*2",
            "94.09%*2",
            "99.01%*2",
            "103.93%*2",
            "108.85%*2"
          ]
        },
        {
          "name": "重击·鸣铁耐力消耗",
          "isSame": true,
          "values": [
            "20",
            "20",
            "20",
            "20",
            "20",
            "20",
            "20",
            "20",
            "20",
            "20",
            "20",
            "20",
            "20",
            "20",
            "20",
            "20",
            "20",
            "20",
            "20",
            "20"
          ]
        },
        {
          "name": "空中攻击耐力消耗",
          "isSame": true,
          "values": [
            "30",
            "30",
            "30",
            "30",
            "30",
            "30",
            "30",
            "30",
            "30",
            "30",
            "30",
            "30",
            "30",
            "30",
            "30",
            "30",
            "30",
            "30",
            "30",
            "30"
          ]
        },
        {
          "name": "空中闪避反击耐力消耗",
          "isSame": true,
          "values": [
            "30",
            "30",
            "30",
            "30",
            "30",
            "30",
            "30",
            "30",
            "30",
            "30",
            "30",
            "30",
            "30",
            "30",
            "30",
            "30",
            "30",
            "30",
            "30",
            "30"
          ]
        },
        {
          "name": "重击·烁雷·后撤伤害",
          "isSame": false,
          "values": [
            "27.00%",
            "29.22%",
            "31.43%",
            "34.53%",
            "36.75%",
            "39.29%",
            "42.84%",
            "46.38%",
            "49.92%",
            "53.68%",
            "58.11%",
            "62.54%",
            "66.97%",
            "71.40%",
            "75.82%",
            "80.25%",
            "84.68%",
            "89.11%",
            "93.54%",
            "97.96%"
          ]
        },
        {
          "name": "重击·烁雷·旋切伤害",
          "isSame": false,
          "values": [
            "71.28%*3",
            "77.13%*3",
            "82.97%*3",
            "91.16%*3",
            "97.00%*3",
            "103.72%*3",
            "113.08%*3",
            "122.43%*3",
            "131.78%*3",
            "141.72%*3",
            "153.41%*3",
            "165.10%*3",
            "176.79%*3",
            "188.48%*3",
            "200.17%*3",
            "211.86%*3",
            "223.55%*3",
            "235.24%*3",
            "246.93%*3",
            "258.62%*3"
          ]
        },
        {
          "name": "重击·烁雷·升拳伤害",
          "isSame": false,
          "values": [
            "90.00%*2",
            "97.38%*2",
            "104.76%*2",
            "115.10%*2",
            "122.48%*2",
            "130.96%*2",
            "142.77%*2",
            "154.58%*2",
            "166.39%*2",
            "178.93%*2",
            "193.69%*2",
            "208.45%*2",
            "223.21%*2",
            "237.97%*2",
            "252.73%*2",
            "267.49%*2",
            "282.25%*2",
            "297.01%*2",
            "311.77%*2",
            "326.53%*2"
          ]
        },
        {
          "name": "闪避反击·重击·鸣铁伤害",
          "isSame": false,
          "values": [
            "23.34%*3",
            "25.25%*3",
            "27.16%*3",
            "29.84%*3",
            "31.76%*3",
            "33.96%*3",
            "37.02%*3",
            "40.08%*3",
            "43.14%*3",
            "46.39%*3",
            "50.22%*3",
            "54.05%*3",
            "57.87%*3",
            "61.70%*3",
            "65.53%*3",
            "69.35%*3",
            "73.18%*3",
            "77.01%*3",
            "80.83%*3",
            "84.66%*3"
          ]
        },
        {
          "name": "闪避反击·烁雷·后撤伤害",
          "isSame": false,
          "values": [
            "27.00%",
            "29.22%",
            "31.43%",
            "34.53%",
            "36.75%",
            "39.29%",
            "42.84%",
            "46.38%",
            "49.92%",
            "53.68%",
            "58.11%",
            "62.54%",
            "66.97%",
            "71.40%",
            "75.82%",
            "80.25%",
            "84.68%",
            "89.11%",
            "93.54%",
            "97.96%"
          ]
        },
        {
          "name": "重击·烁雷·旋切耐力消耗",
          "isSame": true,
          "values": [
            "20",
            "20",
            "20",
            "20",
            "20",
            "20",
            "20",
            "20",
            "20",
            "20",
            "20",
            "20",
            "20",
            "20",
            "20",
            "20",
            "20",
            "20",
            "20",
            "20"
          ]
        },
        {
          "name": "重击·烁雷·升拳耐力消耗",
          "isSame": true,
          "values": [
            "20",
            "20",
            "20",
            "20",
            "20",
            "20",
            "20",
            "20",
            "20",
            "20",
            "20",
            "20",
            "20",
            "20",
            "20",
            "20",
            "20",
            "20",
            "20",
            "20"
          ]
        }
      ]
    },
    "e": {
      "name": "斩锋",
      "desc": [
        "奥古斯塔挥刀跳劈，造成导电伤害。"
      ],
      "tables": [
        {
          "name": "技能伤害",
          "isSame": false,
          "values": [
            "110.00%*3",
            "119.02%*3",
            "128.04%*3",
            "140.67%*3",
            "149.69%*3",
            "160.07%*3",
            "174.50%*3",
            "188.93%*3",
            "203.36%*3",
            "218.70%*3",
            "236.74%*3",
            "254.78%*3",
            "272.82%*3",
            "290.86%*3",
            "308.90%*3",
            "326.94%*3",
            "344.98%*3",
            "363.02%*3",
            "381.06%*3",
            "399.10%*3"
          ]
        },
        {
          "name": "冷却时间",
          "isSame": true,
          "values": [
            "15秒",
            "15秒",
            "15秒",
            "15秒",
            "15秒",
            "15秒",
            "15秒",
            "15秒",
            "15秒",
            "15秒",
            "15秒",
            "15秒",
            "15秒",
            "15秒",
            "15秒",
            "15秒",
            "15秒",
            "15秒",
            "15秒",
            "15秒"
          ]
        },
        {
          "name": "回复协奏能量",
          "isSame": true,
          "values": [
            "10",
            "10",
            "10",
            "10",
            "10",
            "10",
            "10",
            "10",
            "10",
            "10",
            "10",
            "10",
            "10",
            "10",
            "10",
            "10",
            "10",
            "10",
            "10",
            "10"
          ]
        }
      ]
    },
    "q": {
      "name": "至日的征伐",
      "desc": [
        "<h3>共鸣解放·誓锋不殒</h3>",
        "短按共鸣解放松开时可施放该技能，奥古斯塔发动横扫斩击，造成导电伤害，此次伤害为重击伤害。",
        "<h3>共鸣解放·赫日威临</h3>",
        "当存在2层【威慑】时，长按共鸣解放可施放共鸣解放·赫日威临。共鸣解放·赫日威临施放时不消耗共鸣能量，而是消耗2层【威慑】。",
        "·施放共鸣解放·赫日威临时，展开王之界域，并且进入7秒的俯首之刻，俯首之刻持续期间时间暂时停止，不能切换角色，仅能施放赫日威临·烈阳、赫日威临·不朽者之肃、闪避，处于空中状态时可以施放空中攻击。",
        "·俯首之刻期间，短按普攻或长按普攻可施放赫日威临·烈阳。可在水面行走且不消耗耐力。",
        "·若进行场景、玩法、或功能交互时，将强制结束俯首之刻，且不会自动施放赫日威临·不朽者之肃。",
        "<h3>赫日威临·烈阳</h3>",
        "造成导电伤害，此伤害为重击伤害。施放9次赫日威临·烈阳后，短按普攻或共鸣解放可施放赫日威临·不朽者之肃。",
        "<h3>赫日威临·不朽者之肃</h3>",
        "造成导电伤害，此次伤害为重击伤害。施放赫日威临·不朽者之肃时解除俯首之刻，技能结束时消耗全部的【以众愿为冕】，且队伍中除奥古斯塔外的其他角色离场。",
        "·俯首之刻结束时自动施放赫日威临·不朽者之肃。",
        "·俯首之刻持续期间可长按共鸣解放，提前施放赫日威临·不朽者之肃。",
        "<h3>王之界域</h3>",
        "·王之界域持续30秒。",
        "·王之界域存在时：队伍中角色施放变奏技能时，获得基于奥古斯塔最大生命5%+650的护盾，不可叠加，持续10秒。该护盾在切换至其他角色时不会继承。",
        "<h3>【威慑】获取方式</h3>",
        "【威慑】上限为2层。",
        "·施放共鸣技能·不败恒阳·落袭时，奥古斯塔获得1层【威慑】。",
        "·队友处于奥古斯塔延奏技能·不屈的战歌的效果期间，施放延奏技能时，奥古斯塔获得1层【威慑】。"
      ],
      "tables": [
        {
          "name": "共鸣解放·誓锋不殒伤害",
          "isSame": false,
          "values": [
            "16.59%*2+66.36%*3+16.59%*2+287.56%",
            "17.96%*2+71.81%*3+17.96%*2+311.14%",
            "19.32%*2+77.25%*3+19.32%*2+334.72%",
            "21.22%*2+84.87%*3+21.22%*2+367.74%",
            "22.58%*2+90.31%*3+22.58%*2+391.32%",
            "24.15%*2+96.57%*3+24.15%*2+418.43%",
            "26.32%*2+105.27%*3+26.32%*2+456.16%",
            "28.50%*2+113.98%*3+28.50%*2+493.89%",
            "30.67%*2+122.68%*3+30.67%*2+531.62%",
            "32.99%*2+131.94%*3+32.99%*2+571.7%",
            "35.71%*2+142.82%*3+35.71%*2+618.86%",
            "38.43%*2+153.70%*3+38.43%*2+666.02%",
            "41.15%*2+164.58%*3+41.15%*2+713.18%",
            "43.87%*2+175.47%*3+43.87%*2+760.34%",
            "46.59%*2+186.35%*3+46.59%*2+807.5%",
            "49.31%*2+197.23%*3+49.31%*2+854.66%",
            "52.03%*2+208.12%*3+52.03%*2+901.82%",
            "54.75%*2+219.00%*3+54.75%*2+948.98%",
            "57.47%*2+229.88%*3+57.47%*2+996.14%",
            "60.20%*2+240.77%*3+60.20%*2+1043.3%"
          ]
        },
        {
          "name": "赫日威临·烈阳伤害",
          "isSame": false,
          "values": [
            "60.00%",
            "64.92%",
            "69.84%",
            "76.73%",
            "81.65%",
            "87.31%",
            "95.18%",
            "103.05%",
            "110.93%",
            "119.29%",
            "129.13%",
            "138.97%",
            "148.81%",
            "158.65%",
            "168.49%",
            "178.33%",
            "188.17%",
            "198.01%",
            "207.85%",
            "217.69%"
          ]
        },
        {
          "name": "赫日威临·不朽者之肃伤害",
          "isSame": false,
          "values": [
            "120.00%+450.00%+3.00%*10",
            "129.84%+486.90%+3.25%*10",
            "139.68%+523.80%+3.50%*10",
            "153.46%+575.46%+3.84%*10",
            "163.30%+612.36%+4.09%*10",
            "174.62%+654.80%+4.37%*10",
            "190.36%+713.84%+4.76%*10",
            "206.10%+772.88%+5.16%*10",
            "221.85%+831.92%+5.55%*10",
            "238.58%+894.65%+5.97%*10",
            "258.26%+968.45%+6.46%*10",
            "277.94%+1042.25%+6.95%*10",
            "297.62%+1116.05%+7.45%*10",
            "317.30%+1189.85%+7.94%*10",
            "336.98%+1263.65%+8.43%*10",
            "356.66%+1337.45%+8.92%*10",
            "376.34%+1411.25%+9.41%*10",
            "396.02%+1485.05%+9.91%*10",
            "415.70%+1558.85%+10.40%*10",
            "435.38%+1632.65%+10.89%*10"
          ]
        },
        {
          "name": "共鸣解放·誓锋不殒冷却时间",
          "isSame": true,
          "values": [
            "25秒",
            "25秒",
            "25秒",
            "25秒",
            "25秒",
            "25秒",
            "25秒",
            "25秒",
            "25秒",
            "25秒",
            "25秒",
            "25秒",
            "25秒",
            "25秒",
            "25秒",
            "25秒",
            "25秒",
            "25秒",
            "25秒",
            "25秒"
          ]
        },
        {
          "name": "共鸣解放·誓锋不殒消耗共鸣能量",
          "isSame": true,
          "values": [
            "125",
            "125",
            "125",
            "125",
            "125",
            "125",
            "125",
            "125",
            "125",
            "125",
            "125",
            "125",
            "125",
            "125",
            "125",
            "125",
            "125",
            "125",
            "125",
            "125"
          ]
        },
        {
          "name": "共鸣解放·誓锋不殒回复协奏能量",
          "isSame": true,
          "values": [
            "20",
            "20",
            "20",
            "20",
            "20",
            "20",
            "20",
            "20",
            "20",
            "20",
            "20",
            "20",
            "20",
            "20",
            "20",
            "20",
            "20",
            "20",
            "20",
            "20"
          ]
        },
        {
          "name": "共鸣解放·赫日威临冷却时间",
          "isSame": true,
          "values": [
            "25秒",
            "25秒",
            "25秒",
            "25秒",
            "25秒",
            "25秒",
            "25秒",
            "25秒",
            "25秒",
            "25秒",
            "25秒",
            "25秒",
            "25秒",
            "25秒",
            "25秒",
            "25秒",
            "25秒",
            "25秒",
            "25秒",
            "25秒"
          ]
        },
        {
          "name": "赫日威临·不朽者之肃冷却时间",
          "isSame": true,
          "values": [
            "3秒",
            "3秒",
            "3秒",
            "3秒",
            "3秒",
            "3秒",
            "3秒",
            "3秒",
            "3秒",
            "3秒",
            "3秒",
            "3秒",
            "3秒",
            "3秒",
            "3秒",
            "3秒",
            "3秒",
            "3秒",
            "3秒",
            "3秒"
          ]
        }
      ]
    },
    "t": {
      "name": "曜阳如我",
      "desc": [
        "<h3>共鸣技能·不败恒阳·迅击</h3>",
        "【权炳】满时，奥古斯塔的共鸣技能·斩锋替换为共鸣技能·不败恒阳·迅击，造成导电伤害。",
        "·技能施放时，短按普攻或共鸣技能，可以施放共鸣技能·不败恒阳·跃空。",
        "·短时间内被打断则可重新施放共鸣技能·不败恒阳·迅击。",
        "·一定时间后被打断则可施放共鸣技能·不败恒阳·跃空。",
        "·可在空中施放。",
        "<h3>共鸣技能·不败恒阳·跃空</h3>",
        "造成导电伤害。",
        "·技能施放时，短按普攻或共鸣技能，可以施放共鸣技能·不败恒阳·落袭。",
        "·短时间内被打断则可重新施放共鸣技能·不败恒阳·跃空。",
        "·一定时间后被打断则可施放共鸣技能·不败恒阳·落袭。",
        "·仅可在空中施放。",
        "<h3>共鸣技能·不败恒阳·落袭</h3>",
        "施放时消耗全部的【权炳】，造成导电伤害，此次伤害为重击伤害。",
        "·施放时，获得1层【威慑】。",
        "·仅可在空中施放。",
        "<h3>闪避反击·不败恒阳·迅击</h3>",
        "【权炳】满时，地面闪避成功后短按共鸣技能，或者空中闪避成功后短按普攻或共鸣技能，可施放闪避反击·不败恒阳·迅击，施放时造成导电伤害，此次伤害为共鸣技能伤害。",
        "·技能施放时，短按普攻或共鸣技能，可以施放共鸣技能·不败恒阳·跃空。",
        "·一定时间后被打断则可施放共鸣技能·不败恒阳·跃空。",
        "<h3>【权炳】获取规则</h3>",
        "【权炳】上限为100点。",
        "·常态攻击造成伤害时，可以获得【权炳】。",
        "·施放变奏技能·灼金的巡行时回复20%【权炳】。",
        "·施放共鸣技能·斩锋时回复10%【权炳】。",
        "·施放共鸣解放·誓锋不殒时回复40%【权炳】。"
      ],
      "tables": [
        {
          "name": "共鸣技能·不败恒阳·迅击伤害",
          "isSame": false,
          "values": [
            "70.00%*2",
            "75.74%*2",
            "81.48%*2",
            "89.52%*2",
            "95.26%*2",
            "101.86%*2",
            "111.05%*2",
            "120.23%*2",
            "129.41%*2",
            "139.17%*2",
            "150.65%*2",
            "162.13%*2",
            "173.61%*2",
            "185.09%*2",
            "196.57%*2",
            "208.05%*2",
            "219.53%*2",
            "231.01%*2",
            "242.49%*2",
            "253.97%*2"
          ]
        },
        {
          "name": "共鸣技能·不败恒阳·跃空伤害",
          "isSame": false,
          "values": [
            "112.00%+14.00%*2",
            "121.19%+15.15%*2",
            "130.37%+16.30%*2",
            "143.23%+17.91%*2",
            "152.41%+19.06%*2",
            "162.98%+20.38%*2",
            "177.67%+22.21%*2",
            "192.36%+24.05%*2",
            "207.06%+25.89%*2",
            "222.67%+27.84%*2",
            "241.04%+30.13%*2",
            "259.41%+32.43%*2",
            "277.78%+34.73%*2",
            "296.14%+37.02%*2",
            "314.51%+39.32%*2",
            "332.88%+41.61%*2",
            "351.25%+43.91%*2",
            "369.62%+46.21%*2",
            "387.98%+48.50%*2",
            "406.35%+50.80%*2"
          ]
        },
        {
          "name": "共鸣技能·不败恒阳·落袭伤害",
          "isSame": false,
          "values": [
            "43.55%+391.95%",
            "47.13%+424.09%",
            "50.70%+456.23%",
            "55.70%+501.23%",
            "59.27%+533.37%",
            "63.37%+570.33%",
            "69.09%+621.76%",
            "74.80%+673.18%",
            "80.52%+724.60%",
            "86.59%+779.24%",
            "93.73%+843.52%",
            "100.87%+907.80%",
            "108.01%+972.08%",
            "115.16%+1036.36%",
            "122.30%+1100.64%",
            "129.44%+1164.92%",
            "136.58%+1229.20%",
            "143.72%+1293.48%",
            "150.87%+1357.76%",
            "158.01%+1422.04%"
          ]
        },
        {
          "name": "空中闪避反击·不败恒阳·迅击伤害",
          "isSame": false,
          "values": [
            "70.00%*2",
            "75.74%*2",
            "81.48%*2",
            "89.52%*2",
            "95.26%*2",
            "101.86%*2",
            "111.05%*2",
            "120.23%*2",
            "129.41%*2",
            "139.17%*2",
            "150.65%*2",
            "162.13%*2",
            "173.61%*2",
            "185.09%*2",
            "196.57%*2",
            "208.05%*2",
            "219.53%*2",
            "231.01%*2",
            "242.49%*2",
            "253.97%*2"
          ]
        },
        {
          "name": "共鸣技能·不败恒阳·落袭回复协奏能量",
          "isSame": true,
          "values": [
            "7",
            "7",
            "7",
            "7",
            "7",
            "7",
            "7",
            "7",
            "7",
            "7",
            "7",
            "7",
            "7",
            "7",
            "7",
            "7",
            "7",
            "7",
            "7",
            "7"
          ]
        },
        {
          "name": "共鸣技能·不败恒阳·迅击耐力消耗",
          "isSame": true,
          "values": [
            "10",
            "10",
            "10",
            "10",
            "10",
            "10",
            "10",
            "10",
            "10",
            "10",
            "10",
            "10",
            "10",
            "10",
            "10",
            "10",
            "10",
            "10",
            "10",
            "10"
          ]
        },
        {
          "name": "共鸣技能·不败恒阳·跃空耐力消耗",
          "isSame": true,
          "values": [
            "10",
            "10",
            "10",
            "10",
            "10",
            "10",
            "10",
            "10",
            "10",
            "10",
            "10",
            "10",
            "10",
            "10",
            "10",
            "10",
            "10",
            "10",
            "10",
            "10"
          ]
        }
      ]
    },
    "i": {
      "name": "灼金的巡行",
      "desc": [
        "造成导电伤害。"
      ],
      "tables": [
        {
          "name": "技能伤害",
          "isSame": false,
          "values": [
            "50.00%*2",
            "54.10%*2",
            "58.20%*2",
            "63.94%*2",
            "68.04%*2",
            "72.76%*2",
            "79.32%*2",
            "85.88%*2",
            "92.44%*2",
            "99.41%*2",
            "107.61%*2",
            "115.81%*2",
            "124.01%*2",
            "132.21%*2",
            "140.41%*2",
            "148.61%*2",
            "156.81%*2",
            "165.01%*2",
            "173.21%*2",
            "181.41%*2"
          ]
        },
        {
          "name": "回复协奏能量",
          "isSame": true,
          "values": [
            "10",
            "10",
            "10",
            "10",
            "10",
            "10",
            "10",
            "10",
            "10",
            "10",
            "10",
            "10",
            "10",
            "10",
            "10",
            "10",
            "10",
            "10",
            "10",
            "10"
          ]
        }
      ]
    },
    "o": {
      "name": "不屈的战歌",
      "desc": [
        "下一位登场角色获得如下效果，持续14秒，若切换至其他角色则如下效果提前结束：",
        "·全伤害加深15%。",
        "·施放延奏技能时，让队伍中的奥古斯塔获得1层【威慑】与1层【以众愿为冕】。",
        "<h3>【以众愿为冕】</h3>",
        "每层使导电伤害加成提升15%，上限为1层。共鸣解放·赫日威临·不朽者之肃结束时，清除自身全部的【以众愿为冕】。"
      ],
      "tables": []
    }
  },
  "talentData": {
    "a": {
      "第一段伤害": [
        28.9,
        31.27,
        33.64,
        36.96,
        39.33,
        42.06,
        45.85,
        49.64,
        53.43,
        57.46,
        62.2,
        66.94,
        71.68,
        76.42,
        81.16,
        85.9,
        90.64,
        95.38,
        100.12,
        104.86
      ],
      "第二段伤害": [
        67.4,
        72.94,
        78.46,
        86.2,
        91.72,
        98.08,
        106.92,
        115.76,
        124.62,
        134,
        145.06,
        156.12,
        167.16,
        178.22,
        189.28,
        200.32,
        211.38,
        222.44,
        233.5,
        244.54
      ],
      "第二段伤害2": [
        [
          33.7,
          2
        ],
        [
          36.47,
          2
        ],
        [
          39.23,
          2
        ],
        [
          43.1,
          2
        ],
        [
          45.86,
          2
        ],
        [
          49.04,
          2
        ],
        [
          53.46,
          2
        ],
        [
          57.88,
          2
        ],
        [
          62.31,
          2
        ],
        [
          67,
          2
        ],
        [
          72.53,
          2
        ],
        [
          78.06,
          2
        ],
        [
          83.58,
          2
        ],
        [
          89.11,
          2
        ],
        [
          94.64,
          2
        ],
        [
          100.16,
          2
        ],
        [
          105.69,
          2
        ],
        [
          111.22,
          2
        ],
        [
          116.75,
          2
        ],
        [
          122.27,
          2
        ]
      ],
      "第三段伤害": [
        99,
        107.13,
        115.26,
        126.63,
        134.73,
        144.06,
        157.05,
        170.04,
        183.03,
        196.82999999999998,
        213.06,
        229.32,
        245.54999999999998,
        261.78000000000003,
        278.01,
        294.24,
        310.5,
        326.73,
        342.96,
        359.19
      ],
      "第三段伤害2": [
        [
          33,
          3
        ],
        [
          35.71,
          3
        ],
        [
          38.42,
          3
        ],
        [
          42.21,
          3
        ],
        [
          44.91,
          3
        ],
        [
          48.02,
          3
        ],
        [
          52.35,
          3
        ],
        [
          56.68,
          3
        ],
        [
          61.01,
          3
        ],
        [
          65.61,
          3
        ],
        [
          71.02,
          3
        ],
        [
          76.44,
          3
        ],
        [
          81.85,
          3
        ],
        [
          87.26,
          3
        ],
        [
          92.67,
          3
        ],
        [
          98.08,
          3
        ],
        [
          103.5,
          3
        ],
        [
          108.91,
          3
        ],
        [
          114.32,
          3
        ],
        [
          119.73,
          3
        ]
      ],
      "第四段伤害": [
        97.53,
        105.53999999999999,
        113.52000000000001,
        124.71000000000001,
        132.72,
        141.89999999999998,
        154.71,
        167.49,
        180.3,
        193.89,
        209.88,
        225.87,
        241.86,
        257.85,
        273.84000000000003,
        289.83,
        305.82,
        321.81,
        337.83,
        353.82
      ],
      "第四段伤害2": [
        [
          32.51,
          3
        ],
        [
          35.18,
          3
        ],
        [
          37.84,
          3
        ],
        [
          41.57,
          3
        ],
        [
          44.24,
          3
        ],
        [
          47.3,
          3
        ],
        [
          51.57,
          3
        ],
        [
          55.83,
          3
        ],
        [
          60.1,
          3
        ],
        [
          64.63,
          3
        ],
        [
          69.96,
          3
        ],
        [
          75.29,
          3
        ],
        [
          80.62,
          3
        ],
        [
          85.95,
          3
        ],
        [
          91.28,
          3
        ],
        [
          96.61,
          3
        ],
        [
          101.94,
          3
        ],
        [
          107.27,
          3
        ],
        [
          112.61,
          3
        ],
        [
          117.94,
          3
        ]
      ],
      "重击·鸣铁伤害": [
        70.02,
        75.75,
        81.48,
        89.52,
        95.28,
        101.88,
        111.06,
        120.24,
        129.42000000000002,
        139.17000000000002,
        150.66,
        162.14999999999998,
        173.60999999999999,
        185.10000000000002,
        196.59,
        208.04999999999998,
        219.54000000000002,
        231.03000000000003,
        242.49,
        253.98
      ],
      "重击·鸣铁伤害2": [
        [
          23.34,
          3
        ],
        [
          25.25,
          3
        ],
        [
          27.16,
          3
        ],
        [
          29.84,
          3
        ],
        [
          31.76,
          3
        ],
        [
          33.96,
          3
        ],
        [
          37.02,
          3
        ],
        [
          40.08,
          3
        ],
        [
          43.14,
          3
        ],
        [
          46.39,
          3
        ],
        [
          50.22,
          3
        ],
        [
          54.05,
          3
        ],
        [
          57.87,
          3
        ],
        [
          61.7,
          3
        ],
        [
          65.53,
          3
        ],
        [
          69.35,
          3
        ],
        [
          73.18,
          3
        ],
        [
          77.01,
          3
        ],
        [
          80.83,
          3
        ],
        [
          84.66,
          3
        ]
      ],
      "空中攻击伤害": [
        60,
        64.92,
        69.84,
        76.74,
        81.66,
        87.32,
        95.18,
        103.06,
        110.94,
        119.3,
        129.14,
        138.98,
        148.82,
        158.66,
        168.5,
        178.34,
        188.18,
        198.02,
        207.86,
        217.7
      ],
      "空中攻击伤害2": [
        [
          30,
          2
        ],
        [
          32.46,
          2
        ],
        [
          34.92,
          2
        ],
        [
          38.37,
          2
        ],
        [
          40.83,
          2
        ],
        [
          43.66,
          2
        ],
        [
          47.59,
          2
        ],
        [
          51.53,
          2
        ],
        [
          55.47,
          2
        ],
        [
          59.65,
          2
        ],
        [
          64.57,
          2
        ],
        [
          69.49,
          2
        ],
        [
          74.41,
          2
        ],
        [
          79.33,
          2
        ],
        [
          84.25,
          2
        ],
        [
          89.17,
          2
        ],
        [
          94.09,
          2
        ],
        [
          99.01,
          2
        ],
        [
          103.93,
          2
        ],
        [
          108.85,
          2
        ]
      ],
      "闪避反击伤害": [
        67.4,
        72.94,
        78.46,
        86.2,
        91.72,
        98.08,
        106.92,
        115.76,
        124.62,
        134,
        145.06,
        156.12,
        167.16,
        178.22,
        189.28,
        200.32,
        211.38,
        222.44,
        233.5,
        244.54
      ],
      "闪避反击伤害2": [
        [
          33.7,
          2
        ],
        [
          36.47,
          2
        ],
        [
          39.23,
          2
        ],
        [
          43.1,
          2
        ],
        [
          45.86,
          2
        ],
        [
          49.04,
          2
        ],
        [
          53.46,
          2
        ],
        [
          57.88,
          2
        ],
        [
          62.31,
          2
        ],
        [
          67,
          2
        ],
        [
          72.53,
          2
        ],
        [
          78.06,
          2
        ],
        [
          83.58,
          2
        ],
        [
          89.11,
          2
        ],
        [
          94.64,
          2
        ],
        [
          100.16,
          2
        ],
        [
          105.69,
          2
        ],
        [
          111.22,
          2
        ],
        [
          116.75,
          2
        ],
        [
          122.27,
          2
        ]
      ],
      "空中闪避反击伤害": [
        60,
        64.92,
        69.84,
        76.74,
        81.66,
        87.32,
        95.18,
        103.06,
        110.94,
        119.3,
        129.14,
        138.98,
        148.82,
        158.66,
        168.5,
        178.34,
        188.18,
        198.02,
        207.86,
        217.7
      ],
      "空中闪避反击伤害2": [
        [
          30,
          2
        ],
        [
          32.46,
          2
        ],
        [
          34.92,
          2
        ],
        [
          38.37,
          2
        ],
        [
          40.83,
          2
        ],
        [
          43.66,
          2
        ],
        [
          47.59,
          2
        ],
        [
          51.53,
          2
        ],
        [
          55.47,
          2
        ],
        [
          59.65,
          2
        ],
        [
          64.57,
          2
        ],
        [
          69.49,
          2
        ],
        [
          74.41,
          2
        ],
        [
          79.33,
          2
        ],
        [
          84.25,
          2
        ],
        [
          89.17,
          2
        ],
        [
          94.09,
          2
        ],
        [
          99.01,
          2
        ],
        [
          103.93,
          2
        ],
        [
          108.85,
          2
        ]
      ],
      "重击·鸣铁耐力消耗": [
        20,
        20,
        20,
        20,
        20,
        20,
        20,
        20,
        20,
        20,
        20,
        20,
        20,
        20,
        20,
        20,
        20,
        20,
        20,
        20
      ],
      "空中攻击耐力消耗": [
        30,
        30,
        30,
        30,
        30,
        30,
        30,
        30,
        30,
        30,
        30,
        30,
        30,
        30,
        30,
        30,
        30,
        30,
        30,
        30
      ],
      "空中闪避反击耐力消耗": [
        30,
        30,
        30,
        30,
        30,
        30,
        30,
        30,
        30,
        30,
        30,
        30,
        30,
        30,
        30,
        30,
        30,
        30,
        30,
        30
      ],
      "重击·烁雷·后撤伤害": [
        27,
        29.22,
        31.43,
        34.53,
        36.75,
        39.29,
        42.84,
        46.38,
        49.92,
        53.68,
        58.11,
        62.54,
        66.97,
        71.4,
        75.82,
        80.25,
        84.68,
        89.11,
        93.54,
        97.96
      ],
      "重击·烁雷·旋切伤害": [
        213.84,
        231.39,
        248.91,
        273.48,
        291,
        311.15999999999997,
        339.24,
        367.29,
        395.34000000000003,
        425.15999999999997,
        460.23,
        495.29999999999995,
        530.37,
        565.4399999999999,
        600.51,
        635.58,
        670.6500000000001,
        705.72,
        740.79,
        775.86
      ],
      "重击·烁雷·旋切伤害2": [
        [
          71.28,
          3
        ],
        [
          77.13,
          3
        ],
        [
          82.97,
          3
        ],
        [
          91.16,
          3
        ],
        [
          97,
          3
        ],
        [
          103.72,
          3
        ],
        [
          113.08,
          3
        ],
        [
          122.43,
          3
        ],
        [
          131.78,
          3
        ],
        [
          141.72,
          3
        ],
        [
          153.41,
          3
        ],
        [
          165.1,
          3
        ],
        [
          176.79,
          3
        ],
        [
          188.48,
          3
        ],
        [
          200.17,
          3
        ],
        [
          211.86,
          3
        ],
        [
          223.55,
          3
        ],
        [
          235.24,
          3
        ],
        [
          246.93,
          3
        ],
        [
          258.62,
          3
        ]
      ],
      "重击·烁雷·升拳伤害": [
        180,
        194.76,
        209.52,
        230.2,
        244.96,
        261.92,
        285.54,
        309.16,
        332.78,
        357.86,
        387.38,
        416.9,
        446.42,
        475.94,
        505.46,
        534.98,
        564.5,
        594.02,
        623.54,
        653.06
      ],
      "重击·烁雷·升拳伤害2": [
        [
          90,
          2
        ],
        [
          97.38,
          2
        ],
        [
          104.76,
          2
        ],
        [
          115.1,
          2
        ],
        [
          122.48,
          2
        ],
        [
          130.96,
          2
        ],
        [
          142.77,
          2
        ],
        [
          154.58,
          2
        ],
        [
          166.39,
          2
        ],
        [
          178.93,
          2
        ],
        [
          193.69,
          2
        ],
        [
          208.45,
          2
        ],
        [
          223.21,
          2
        ],
        [
          237.97,
          2
        ],
        [
          252.73,
          2
        ],
        [
          267.49,
          2
        ],
        [
          282.25,
          2
        ],
        [
          297.01,
          2
        ],
        [
          311.77,
          2
        ],
        [
          326.53,
          2
        ]
      ],
      "闪避反击·重击·鸣铁伤害": [
        70.02,
        75.75,
        81.48,
        89.52,
        95.28,
        101.88,
        111.06,
        120.24,
        129.42000000000002,
        139.17000000000002,
        150.66,
        162.14999999999998,
        173.60999999999999,
        185.10000000000002,
        196.59,
        208.04999999999998,
        219.54000000000002,
        231.03000000000003,
        242.49,
        253.98
      ],
      "闪避反击·重击·鸣铁伤害2": [
        [
          23.34,
          3
        ],
        [
          25.25,
          3
        ],
        [
          27.16,
          3
        ],
        [
          29.84,
          3
        ],
        [
          31.76,
          3
        ],
        [
          33.96,
          3
        ],
        [
          37.02,
          3
        ],
        [
          40.08,
          3
        ],
        [
          43.14,
          3
        ],
        [
          46.39,
          3
        ],
        [
          50.22,
          3
        ],
        [
          54.05,
          3
        ],
        [
          57.87,
          3
        ],
        [
          61.7,
          3
        ],
        [
          65.53,
          3
        ],
        [
          69.35,
          3
        ],
        [
          73.18,
          3
        ],
        [
          77.01,
          3
        ],
        [
          80.83,
          3
        ],
        [
          84.66,
          3
        ]
      ],
      "闪避反击·烁雷·后撤伤害": [
        27,
        29.22,
        31.43,
        34.53,
        36.75,
        39.29,
        42.84,
        46.38,
        49.92,
        53.68,
        58.11,
        62.54,
        66.97,
        71.4,
        75.82,
        80.25,
        84.68,
        89.11,
        93.54,
        97.96
      ],
      "重击·烁雷·旋切耐力消耗": [
        20,
        20,
        20,
        20,
        20,
        20,
        20,
        20,
        20,
        20,
        20,
        20,
        20,
        20,
        20,
        20,
        20,
        20,
        20,
        20
      ],
      "重击·烁雷·升拳耐力消耗": [
        20,
        20,
        20,
        20,
        20,
        20,
        20,
        20,
        20,
        20,
        20,
        20,
        20,
        20,
        20,
        20,
        20,
        20,
        20,
        20
      ]
    },
    "e": {
      "技能伤害": [
        330,
        357.06,
        384.12,
        422.01,
        449.07,
        480.21,
        523.5,
        566.79,
        610.08,
        656.0999999999999,
        710.22,
        764.34,
        818.46,
        872.58,
        926.6999999999999,
        980.8199999999999,
        1034.94,
        1089.06,
        1143.18,
        1197.3000000000002
      ],
      "技能伤害2": [
        [
          110,
          3
        ],
        [
          119.02,
          3
        ],
        [
          128.04,
          3
        ],
        [
          140.67,
          3
        ],
        [
          149.69,
          3
        ],
        [
          160.07,
          3
        ],
        [
          174.5,
          3
        ],
        [
          188.93,
          3
        ],
        [
          203.36,
          3
        ],
        [
          218.7,
          3
        ],
        [
          236.74,
          3
        ],
        [
          254.78,
          3
        ],
        [
          272.82,
          3
        ],
        [
          290.86,
          3
        ],
        [
          308.9,
          3
        ],
        [
          326.94,
          3
        ],
        [
          344.98,
          3
        ],
        [
          363.02,
          3
        ],
        [
          381.06,
          3
        ],
        [
          399.1,
          3
        ]
      ],
      "冷却时间": [
        15,
        15,
        15,
        15,
        15,
        15,
        15,
        15,
        15,
        15,
        15,
        15,
        15,
        15,
        15,
        15,
        15,
        15,
        15,
        15
      ],
      "回复协奏能量": [
        10,
        10,
        10,
        10,
        10,
        10,
        10,
        10,
        10,
        10,
        10,
        10,
        10,
        10,
        10,
        10,
        10,
        10,
        10,
        10
      ]
    },
    "q": {
      "共鸣解放·誓锋不殒伤害": [
        387.1,
        418.87,
        450.61,
        495.05,
        526.79,
        563.3,
        614.07,
        664.87,
        715.6400000000001,
        769.6200000000001,
        833.1,
        896.5799999999999,
        960.06,
        1023.55,
        1087.03,
        1150.51,
        1214,
        1277.48,
        1340.96,
        1404.47
      ],
      "共鸣解放·誓锋不殒伤害2": [
        [
          16.59,
          66.36,
          16.59,
          287.56
        ],
        [
          17.96,
          71.81,
          17.96,
          311.14
        ],
        [
          19.32,
          77.25,
          19.32,
          334.72
        ],
        [
          21.22,
          84.87,
          21.22,
          367.74
        ],
        [
          22.58,
          90.31,
          22.58,
          391.32
        ],
        [
          24.15,
          96.57,
          24.15,
          418.43
        ],
        [
          26.32,
          105.27,
          26.32,
          456.16
        ],
        [
          28.5,
          113.98,
          28.5,
          493.89
        ],
        [
          30.67,
          122.68,
          30.67,
          531.62
        ],
        [
          32.99,
          131.94,
          32.99,
          571.7
        ],
        [
          35.71,
          142.82,
          35.71,
          618.86
        ],
        [
          38.43,
          153.7,
          38.43,
          666.02
        ],
        [
          41.15,
          164.58,
          41.15,
          713.18
        ],
        [
          43.87,
          175.47,
          43.87,
          760.34
        ],
        [
          46.59,
          186.35,
          46.59,
          807.5
        ],
        [
          49.31,
          197.23,
          49.31,
          854.66
        ],
        [
          52.03,
          208.12,
          52.03,
          901.82
        ],
        [
          54.75,
          219,
          54.75,
          948.98
        ],
        [
          57.47,
          229.88,
          57.47,
          996.14
        ],
        [
          60.2,
          240.77,
          60.2,
          1043.3
        ]
      ],
      "赫日威临·烈阳伤害": [
        60,
        64.92,
        69.84,
        76.73,
        81.65,
        87.31,
        95.18,
        103.05,
        110.93,
        119.29,
        129.13,
        138.97,
        148.81,
        158.65,
        168.49,
        178.33,
        188.17,
        198.01,
        207.85,
        217.69
      ],
      "赫日威临·不朽者之肃伤害": [
        573,
        619.99,
        666.98,
        732.7600000000001,
        779.7500000000001,
        833.79,
        908.96,
        984.14,
        1059.32,
        1139.2,
        1233.17,
        1327.14,
        1421.1200000000001,
        1515.09,
        1609.0600000000002,
        1703.0300000000002,
        1797,
        1890.98,
        1984.95,
        2078.92
      ],
      "赫日威临·不朽者之肃伤害2": [
        [
          120,
          450,
          3
        ],
        [
          129.84,
          486.9,
          3.25
        ],
        [
          139.68,
          523.8,
          3.5
        ],
        [
          153.46,
          575.46,
          3.84
        ],
        [
          163.3,
          612.36,
          4.09
        ],
        [
          174.62,
          654.8,
          4.37
        ],
        [
          190.36,
          713.84,
          4.76
        ],
        [
          206.1,
          772.88,
          5.16
        ],
        [
          221.85,
          831.92,
          5.55
        ],
        [
          238.58,
          894.65,
          5.97
        ],
        [
          258.26,
          968.45,
          6.46
        ],
        [
          277.94,
          1042.25,
          6.95
        ],
        [
          297.62,
          1116.05,
          7.45
        ],
        [
          317.3,
          1189.85,
          7.94
        ],
        [
          336.98,
          1263.65,
          8.43
        ],
        [
          356.66,
          1337.45,
          8.92
        ],
        [
          376.34,
          1411.25,
          9.41
        ],
        [
          396.02,
          1485.05,
          9.91
        ],
        [
          415.7,
          1558.85,
          10.4
        ],
        [
          435.38,
          1632.65,
          10.89
        ]
      ],
      "共鸣解放·誓锋不殒冷却时间": [
        25,
        25,
        25,
        25,
        25,
        25,
        25,
        25,
        25,
        25,
        25,
        25,
        25,
        25,
        25,
        25,
        25,
        25,
        25,
        25
      ],
      "共鸣解放·誓锋不殒消耗共鸣能量": [
        125,
        125,
        125,
        125,
        125,
        125,
        125,
        125,
        125,
        125,
        125,
        125,
        125,
        125,
        125,
        125,
        125,
        125,
        125,
        125
      ],
      "共鸣解放·誓锋不殒回复协奏能量": [
        20,
        20,
        20,
        20,
        20,
        20,
        20,
        20,
        20,
        20,
        20,
        20,
        20,
        20,
        20,
        20,
        20,
        20,
        20,
        20
      ],
      "共鸣解放·赫日威临冷却时间": [
        25,
        25,
        25,
        25,
        25,
        25,
        25,
        25,
        25,
        25,
        25,
        25,
        25,
        25,
        25,
        25,
        25,
        25,
        25,
        25
      ],
      "赫日威临·不朽者之肃冷却时间": [
        3,
        3,
        3,
        3,
        3,
        3,
        3,
        3,
        3,
        3,
        3,
        3,
        3,
        3,
        3,
        3,
        3,
        3,
        3,
        3
      ]
    },
    "t": {
      "共鸣技能·不败恒阳·迅击伤害": [
        140,
        151.48,
        162.96,
        179.04,
        190.52,
        203.72,
        222.1,
        240.46,
        258.82,
        278.34,
        301.3,
        324.26,
        347.22,
        370.18,
        393.14,
        416.1,
        439.06,
        462.02,
        484.98,
        507.94
      ],
      "共鸣技能·不败恒阳·迅击伤害2": [
        [
          70,
          2
        ],
        [
          75.74,
          2
        ],
        [
          81.48,
          2
        ],
        [
          89.52,
          2
        ],
        [
          95.26,
          2
        ],
        [
          101.86,
          2
        ],
        [
          111.05,
          2
        ],
        [
          120.23,
          2
        ],
        [
          129.41,
          2
        ],
        [
          139.17,
          2
        ],
        [
          150.65,
          2
        ],
        [
          162.13,
          2
        ],
        [
          173.61,
          2
        ],
        [
          185.09,
          2
        ],
        [
          196.57,
          2
        ],
        [
          208.05,
          2
        ],
        [
          219.53,
          2
        ],
        [
          231.01,
          2
        ],
        [
          242.49,
          2
        ],
        [
          253.97,
          2
        ]
      ],
      "共鸣技能·不败恒阳·跃空伤害": [
        126,
        136.34,
        146.67000000000002,
        161.14,
        171.47,
        183.35999999999999,
        199.88,
        216.41000000000003,
        232.95,
        250.51,
        271.17,
        291.84000000000003,
        312.51,
        333.15999999999997,
        353.83,
        374.49,
        395.15999999999997,
        415.83,
        436.48,
        457.15000000000003
      ],
      "共鸣技能·不败恒阳·跃空伤害2": [
        [
          112,
          14
        ],
        [
          121.19,
          15.15
        ],
        [
          130.37,
          16.3
        ],
        [
          143.23,
          17.91
        ],
        [
          152.41,
          19.06
        ],
        [
          162.98,
          20.38
        ],
        [
          177.67,
          22.21
        ],
        [
          192.36,
          24.05
        ],
        [
          207.06,
          25.89
        ],
        [
          222.67,
          27.84
        ],
        [
          241.04,
          30.13
        ],
        [
          259.41,
          32.43
        ],
        [
          277.78,
          34.73
        ],
        [
          296.14,
          37.02
        ],
        [
          314.51,
          39.32
        ],
        [
          332.88,
          41.61
        ],
        [
          351.25,
          43.91
        ],
        [
          369.62,
          46.21
        ],
        [
          387.98,
          48.5
        ],
        [
          406.35,
          50.8
        ]
      ],
      "共鸣技能·不败恒阳·落袭伤害": [
        435.5,
        471.21999999999997,
        506.93,
        556.9300000000001,
        592.64,
        633.7,
        690.85,
        747.9799999999999,
        805.12,
        865.83,
        937.25,
        1008.67,
        1080.0900000000001,
        1151.52,
        1222.94,
        1294.3600000000001,
        1365.78,
        1437.2,
        1508.63,
        1580.05
      ],
      "共鸣技能·不败恒阳·落袭伤害2": [
        [
          43.55,
          391.95
        ],
        [
          47.13,
          424.09
        ],
        [
          50.7,
          456.23
        ],
        [
          55.7,
          501.23
        ],
        [
          59.27,
          533.37
        ],
        [
          63.37,
          570.33
        ],
        [
          69.09,
          621.76
        ],
        [
          74.8,
          673.18
        ],
        [
          80.52,
          724.6
        ],
        [
          86.59,
          779.24
        ],
        [
          93.73,
          843.52
        ],
        [
          100.87,
          907.8
        ],
        [
          108.01,
          972.08
        ],
        [
          115.16,
          1036.36
        ],
        [
          122.3,
          1100.64
        ],
        [
          129.44,
          1164.92
        ],
        [
          136.58,
          1229.2
        ],
        [
          143.72,
          1293.48
        ],
        [
          150.87,
          1357.76
        ],
        [
          158.01,
          1422.04
        ]
      ],
      "空中闪避反击·不败恒阳·迅击伤害": [
        140,
        151.48,
        162.96,
        179.04,
        190.52,
        203.72,
        222.1,
        240.46,
        258.82,
        278.34,
        301.3,
        324.26,
        347.22,
        370.18,
        393.14,
        416.1,
        439.06,
        462.02,
        484.98,
        507.94
      ],
      "空中闪避反击·不败恒阳·迅击伤害2": [
        [
          70,
          2
        ],
        [
          75.74,
          2
        ],
        [
          81.48,
          2
        ],
        [
          89.52,
          2
        ],
        [
          95.26,
          2
        ],
        [
          101.86,
          2
        ],
        [
          111.05,
          2
        ],
        [
          120.23,
          2
        ],
        [
          129.41,
          2
        ],
        [
          139.17,
          2
        ],
        [
          150.65,
          2
        ],
        [
          162.13,
          2
        ],
        [
          173.61,
          2
        ],
        [
          185.09,
          2
        ],
        [
          196.57,
          2
        ],
        [
          208.05,
          2
        ],
        [
          219.53,
          2
        ],
        [
          231.01,
          2
        ],
        [
          242.49,
          2
        ],
        [
          253.97,
          2
        ]
      ],
      "共鸣技能·不败恒阳·落袭回复协奏能量": [
        7,
        7,
        7,
        7,
        7,
        7,
        7,
        7,
        7,
        7,
        7,
        7,
        7,
        7,
        7,
        7,
        7,
        7,
        7,
        7
      ],
      "共鸣技能·不败恒阳·迅击耐力消耗": [
        10,
        10,
        10,
        10,
        10,
        10,
        10,
        10,
        10,
        10,
        10,
        10,
        10,
        10,
        10,
        10,
        10,
        10,
        10,
        10
      ],
      "共鸣技能·不败恒阳·跃空耐力消耗": [
        10,
        10,
        10,
        10,
        10,
        10,
        10,
        10,
        10,
        10,
        10,
        10,
        10,
        10,
        10,
        10,
        10,
        10,
        10,
        10
      ]
    },
    "i": {
      "技能伤害": [
        100,
        108.2,
        116.4,
        127.88,
        136.08,
        145.52,
        158.64,
        171.76,
        184.88,
        198.82,
        215.22,
        231.62,
        248.02,
        264.42,
        280.82,
        297.22,
        313.62,
        330.02,
        346.42,
        362.82
      ],
      "技能伤害2": [
        [
          50,
          2
        ],
        [
          54.1,
          2
        ],
        [
          58.2,
          2
        ],
        [
          63.94,
          2
        ],
        [
          68.04,
          2
        ],
        [
          72.76,
          2
        ],
        [
          79.32,
          2
        ],
        [
          85.88,
          2
        ],
        [
          92.44,
          2
        ],
        [
          99.41,
          2
        ],
        [
          107.61,
          2
        ],
        [
          115.81,
          2
        ],
        [
          124.01,
          2
        ],
        [
          132.21,
          2
        ],
        [
          140.41,
          2
        ],
        [
          148.61,
          2
        ],
        [
          156.81,
          2
        ],
        [
          165.01,
          2
        ],
        [
          173.21,
          2
        ],
        [
          181.41,
          2
        ]
      ],
      "回复协奏能量": [
        10,
        10,
        10,
        10,
        10,
        10,
        10,
        10,
        10,
        10,
        10,
        10,
        10,
        10,
        10,
        10,
        10,
        10,
        10,
        10
      ]
    },
    "o": {}
  },
  "cons": {
    "1": {
      "name": "于焦壤中蒙垢",
      "desc": [
        "·【以众愿为冕】每层使暴击伤害额外提升15%。",
        "·【以众愿为冕】上限提高至2层。",
        "·奥古斯塔施放变奏技能·灼金的巡行时，也可以获得1层【以众愿为冕】。",
        "·共鸣技能·不败恒阳·迅击、共鸣技能·不败恒阳·跃空、共鸣技能·不败恒阳·落袭免疫打断。"
      ]
    },
    "2": {
      "name": "于血戮中涤尘",
      "desc": [
        "·【以众愿为冕】获得额外效果：每层使暴击提升20%。 ",
        "·奥古斯塔暴击高于100%时，每多出1%暴击，奥古斯塔暴击伤害提升2%，最高可提升100%暴击伤害。"
      ]
    },
    "3": {
      "name": "于朽腐中砺骨",
      "desc": [
        "以下技能的伤害倍率提升25%：",
        "·重击·烁雷·后撤、闪避反击·烁雷·后撤、重击·烁雷·旋切、重击·烁雷·升拳。",
        "·共鸣技能·不败恒阳·落袭。",
        "·共鸣解放·赫日威临·烈阳、共鸣解放·赫日威临·不朽者之肃。"
      ]
    },
    "4": {
      "name": "于荣辉中孤行",
      "desc": [
        "施放变奏技能·灼金的巡行时，队伍中的角色的攻击提升20%，持续30秒。"
      ]
    },
    "5": {
      "name": "于怒潮中卓立",
      "desc": [
        "固有技能·荣誉的加护获得护盾量提升50%。"
      ]
    },
    "6": {
      "name": "于耀光中刻名",
      "desc": [
        "·【以众愿为冕】的上限提升至4层。",
        "·奥古斯塔暴击高于150%时，每多出1%暴击，奥古斯塔暴击伤害提升2%，最高可提升50%暴击伤害。",
        "·奥古斯塔施放重击·烁雷·旋切、重击·烁雷·升拳时，可以获得2层【以众愿为冕】，每1秒仅可通过于耀光中刻名的效果获得2层【以众愿为冕】。",
        "·施放重击·烁雷·旋切、重击·烁雷·升拳过程中，会在原地额外引发【怒霆】，造成两次奥古斯塔攻击100%的导电伤害，此次伤害为重击伤害。"
      ]
    }
  },
  "passive": [
    {
      "name": "荣誉的加护",
      "desc": [
        "奥古斯塔造成伤害时，获得最大生命2.5%+350的护盾，不可叠加，持续5秒，每0.5秒可生效1次。该护盾在切换至其他角色时不会继承。"
      ]
    },
    {
      "name": "炽盛决意",
      "desc": [
        "奥古斯塔处于非战斗状态大于4秒时，获得如下效果，每4秒可生效1次：",
        "·若【威慑】少于1层，则补至1层。",
        "·【以众愿为冕】补充至上限。"
      ]
    }
  ],
  "attr": {
    "tree": {
      "1": {
        "name": "暴击提升1.20%",
        "key": "暴击提升",
        "value": 1.2
      },
      "2": {
        "name": "攻击提升1.80%",
        "key": "攻击提升",
        "value": 1.8
      },
      "3": {
        "name": "攻击提升1.80%",
        "key": "攻击提升",
        "value": 1.8
      },
      "4": {
        "name": "暴击提升1.20%",
        "key": "暴击提升",
        "value": 1.2
      },
      "5": {
        "name": "暴击提升2.80%",
        "key": "暴击提升",
        "value": 2.8
      },
      "6": {
        "name": "攻击提升4.20%",
        "key": "攻击提升",
        "value": 4.2
      },
      "7": {
        "name": "攻击提升4.20%",
        "key": "攻击提升",
        "value": 4.2
      },
      "8": {
        "name": "暴击提升2.80%",
        "key": "暴击提升",
        "value": 2.8
      }
    },
    "details": {
      "1": [
        824,
        37,
        91
      ],
      "20": [
        2143.3064,
        96.2407,
        233.4605
      ],
      "40": [
        4081.3544,
        186.3505,
        442.4056
      ],
      "50": [
        5325.1,
        245.2804,
        576.3667
      ],
      "60": [
        6568.8456,
        304.2103,
        710.3278
      ],
      "70": [
        7812.5088,
        363.1402,
        844.2889
      ],
      "80": [
        9056.2544,
        412.8201,
        978.2591
      ],
      "90": [
        10300,
        462.5,
        1112.2202
      ],
      "20+": [
        2692.5848,
        123.9907,
        292.4376
      ],
      "40+": [
        4630.7152,
        214.1005,
        501.3827
      ],
      "50+": [
        5874.4608,
        273.0304,
        635.3438
      ],
      "60+": [
        7118.124,
        331.9603,
        769.314
      ],
      "70+": [
        8361.8696,
        381.6402,
        903.2751
      ],
      "80+": [
        9605.6152,
        431.3201,
        1037.2362
      ]
    }
  }
}