{
  "id": 6000059,
  "Name": "角",
  "Code": "Z01-",
  "desc": "短暂地召唤「角」攻击敌人，造成衍射伤害。施放声骸技能后，角色的共鸣技能可令敌人受到持续的衍射伤害。",
  "affixData": {
    "text": "使用声骸技能，召唤「角」腾跃而起，对目标造成$[0]的衍射伤害并降下光雷，光雷对周围目标造成最多五段，每段$[1]的衍射伤害。随后「角」向下盘旋攻击周围敌人，连续两次造成$[2]的衍射伤害。施放声骸技能时，获得「光阴之祝」，持续$[3]秒。「光阴之祝」持续期间：·自身的共鸣技能伤害加成提升$[4]；·自身的共鸣技能命中目标后，目标每秒受到1次$[5]衍射伤害，此次伤害为角色的共鸣技能伤害，持续$[6]秒。技能冷却：$[7]秒",
    "datas": {
      "0": [
        "30.40%",
        "34.96%",
        "39.52%",
        "44.08%",
        "48.64%"
      ],
      "1": [
        "12.16%",
        "13.98%",
        "15.81%",
        "17.63%",
        "19.46%"
      ],
      "2": [
        "30.40%",
        "34.96%",
        "39.52%",
        "44.08%",
        "48.64%"
      ],
      "3": [
        "15",
        "15",
        "15",
        "15",
        "15"
      ],
      "4": [
        "16.00%",
        "16.00%",
        "16.00%",
        "16.00%",
        "16.00%"
      ],
      "5": [
        "10.00%",
        "11.50%",
        "13.00%",
        "14.50%",
        "16.00%"
      ],
      "6": [
        "15",
        "15",
        "15",
        "15",
        "15"
      ],
      "7": [
        "20",
        "20",
        "20",
        "20",
        "20"
      ]
    }
  }
}